{"cameraMode":{"drawMode":0,"name":"Shaded","section":"Shading Mode"},"sceneLighting":false,"audioPlay":false,"sceneViewState":{"m_AlwaysRefresh":false,"showFog":true,"showSkybox":false,"showFlares":true,"showImageEffects":true,"showParticleSystems":true,"showVisualEffectGraphs":true,"m_FxEnabled":true},"in2DMode":false,"pivot":{"x":0.0,"y":0.0,"z":0.0},"rotation":{"x":0.2463349550962448,"y":0.027617281302809717,"z":-0.007022433914244175,"w":0.9687661528587341},"size":2.3080480098724367,"orthographic":false}